flet_math/__init__.py
flet_math/flet_math.py
flutter/flet_math/CHANGELOG.md
flutter/flet_math/LICENSE
flutter/flet_math/README.md
flutter/flet_math/pubspec.lock
flutter/flet_math/pubspec.yaml
flutter/flet_math/lib/flet_math.dart
flutter/flet_math/lib/src/create_control.dart
flutter/flet_math/lib/src/flet_math.dart
flet_math-0.1.1.dist-info/METADATA
flet_math-0.1.1.dist-info/WHEEL
flet_math-0.1.1.dist-info/top_level.txt
flet_math-0.1.1.dist-info/RECORD
