Metadata-Version: 2.2
Name: flet_math
Version: 0.1.1
Summary: FletMath control for Flet
Author-email: Flet contributors <you@example.com>
Project-URL: Homepage, https://mydomain.dev
Project-URL: Documentation, https://github.com/MyGithubAccount/flet-math
Project-URL: Repository, https://github.com/MyGithubAccount/flet-math
Project-URL: Issues, https://github.com/MyGithubAccount/flet-math/issues
Requires-Python: >=3.9
Requires-Dist: flet>=0.27.5
